anatrans/__init__.py
anatrans/example_notebook.ipynb
anatrans/analysis/__init__.py
anatrans/analysis/mass_balance.py
anatrans/analysis/parameter_calculations.py
anatrans/bioscreen/__init__.py
anatrans/bioscreen/analysis/__init__.py
anatrans/bioscreen/data/__init__.py
anatrans/bioscreen/transport/__init__.py
anatrans/bioscreen/vizualize/__init__.py
anatrans/data/__init__.py
anatrans/data/check_input.py
anatrans/data/parameter_information.py
anatrans/data/read.py
anatrans/transport/__init__.py
anatrans/transport/analytical_equation.py
anatrans/visualize/__init__.py
anatrans/visualize/plot_line.py
anatrans/visualize/plot_surface.py
anatrans/visualize/show_mass_balance.py
anatrans-0.2.0.dist-info/LICENSE
anatrans-0.2.0.dist-info/METADATA
anatrans-0.2.0.dist-info/WHEEL
anatrans-0.2.0.dist-info/top_level.txt
anatrans-0.2.0.dist-info/RECORD
