Metadata-Version: 2.2
Name: anatrans
Version: 0.2.0
Summary: A collection of analytical and semi-semianalytical solutions for hydrogeological transport phenomena
Author: Sona Aseyednezhad, Robin Richardson, Jaro Camphuijsen, Jorrit Yvo Bakker
Author-email: Alraune Zech <a.zech@uu.nl>
License: 
Project-URL: Repository, https://github.com/MiBiPreT/anatrans
Project-URL: Issues, https://github.com/MiBiPreT/anatrans/issues
Project-URL: Changelog, https://github.com/MiBiPreT/anatrans/CHANGELOG.md
Keywords: groundwater,contaminant transport
Classifier: Development Status :: 2 - Pre-Alpha
Classifier: Intended Audience :: Developers
Classifier: Intended Audience :: Science/Research
Classifier: License :: OSI Approved :: Apache Software License
Classifier: Natural Language :: English
Classifier: Programming Language :: Python :: 3
Classifier: Programming Language :: Python :: 3.8
Classifier: Programming Language :: Python :: 3.9
Classifier: Programming Language :: Python :: 3.10
Classifier: Programming Language :: Python :: 3.11
Classifier: Programming Language :: Python :: 3.12
Requires-Python: >=3.8
License-File: LICENSE
Requires-Dist: contourpy
Requires-Dist: cycler
Requires-Dist: fonttools
Requires-Dist: iniconfig
Requires-Dist: kiwisolver
Requires-Dist: matplotlib
Requires-Dist: numpy
Requires-Dist: packaging
Requires-Dist: pandas
Requires-Dist: pillow
Requires-Dist: pluggy
Requires-Dist: prettytable
Requires-Dist: pyparsing
Requires-Dist: pytest
Requires-Dist: python-dateutil
Requires-Dist: pytz
Requires-Dist: ruff
Requires-Dist: scipy
Requires-Dist: six
Requires-Dist: tzdata
Requires-Dist: wcwidth
Provides-Extra: dev
Requires-Dist: build; extra == "dev"
Requires-Dist: bump-my-version; extra == "dev"
Requires-Dist: coverage[toml]; extra == "dev"
Requires-Dist: pytest; extra == "dev"
Requires-Dist: pytest-cov; extra == "dev"
Requires-Dist: ruff; extra == "dev"
Requires-Dist: tox; extra == "dev"
Provides-Extra: publishing
Requires-Dist: build; extra == "publishing"
Requires-Dist: twine; extra == "publishing"
Requires-Dist: wheel; extra == "publishing"
Provides-Extra: doc
Requires-Dist: mkdocs>=1.4.2; extra == "doc"
Requires-Dist: mkdocs-material>=8.2.7; extra == "doc"
Requires-Dist: mkdocstrings[python]>=0.19.1; extra == "doc"
Requires-Dist: mdx-include>=1.4.1; extra == "doc"
Requires-Dist: mkdocs-markdownextradata-plugin>=0.2.5; extra == "doc"
